{"name": "CRUCIARUS", "traits": "Incorporeal,Undead,", "level": 9, "specials": [{"name": "Tortured Gaze", "actions": "one", "type": "offense", "description": "(visual) The cruciarus can channel the excruciating pain it felt as it died of doghousing against a target within 30 feet of it. The target must make a basic DC 31 Fortitude save against 6d4 points of mental damage. On a failure, the target is also fatigued."}, {"name": "Pain Touch", "actions": "", "type": "offense", "description": "A cruciarus\u2019 attacks cause wracking, agonizing pains to tear through a victim\u2019s body. It ignores all kinds of resistances, but does not harm undead. Creatures affected by pain touch make a DC 31 Fortitude save or become stunned 1 from the pain."}, {"name": "", "actions": "", "type": "offense", "description": ""}, {"name": "", "actions": "", "type": "offense", "description": "The stunned condition from a cruciarus can stack with itself or other cruciaruses\u2019."}], "morespells": [], "alignment": "LE", "size": "Medium", "type": "-", "description": "", "items": "", "spellattack": "", "spelldc": "", "savenote": "", "speed": "fly 30 feet", "spelltype": "", "focuspoints": "", "cantriplevel": "", "spells": [], "constant": "", "strength": {"value": "+7"}, "dexterity": {"value": "+3"}, "constitution": {"value": "+5"}, "intelligence": {"value": "+4"}, "wisdom": {"value": "+5"}, "charisma": {"value": "+5"}, "perception": {"value": "+22", "note": " darkvision"}, "acrobatics": {}, "arcana": {}, "athletics": {}, "crafting": {}, "deception": {}, "diplomacy": {}, "intimidation": {}, "medicine": {}, "nature": {}, "occultism": {}, "performance": {}, "religion": {}, "society": {}, "stealth": {}, "survival": {}, "thievery": {}, "lore": {}, "ac": {"value": "31"}, "hp": {"value": "175 (negative healing)"}, "fortitude": {"value": "+20"}, "reflex": {"value": "+18"}, "will": {"value": "+24"}, "resistance": {}, "weakness": {}, "immunity": {"value": "death effects, disease, paralyzed, poison, spell deflection, unconscious"}, "strikes": [{"name": "pain", "traits": "agile", "attack": "touch", "damage": "6d6 negative plus pain touch", "type": "Melee"}], "languages": ""}